triplify_csv/__init__.py
triplify_csv/triplify_csv.py
triplify_csv-0.5.1.dist-info/LICENSE
triplify_csv-0.5.1.dist-info/METADATA
triplify_csv-0.5.1.dist-info/WHEEL
triplify_csv-0.5.1.dist-info/entry_points.txt
triplify_csv-0.5.1.dist-info/RECORD
