Metadata-Version: 2.1
Name: triplify-csv
Version: 0.5.1
Summary: A tool to generate triples from CSV files according to a configuration file.
Home-page: https://github.com/AAtley/triplify_csv
License: BSD-3-Clause
Author: Adrian Atley
Requires-Python: >=3.7,<4.0
Classifier: License :: OSI Approved :: BSD License
Classifier: Programming Language :: Python :: 3
Classifier: Programming Language :: Python :: 3.7
Classifier: Programming Language :: Python :: 3.8
Classifier: Programming Language :: Python :: 3.9
Classifier: Programming Language :: Python :: 3.10
Classifier: Programming Language :: Python :: 3.11
Requires-Dist: click (>=8.1.3,<9.0.0)
Requires-Dist: pytest (>=7.3.0,<8.0.0)
Requires-Dist: rdflib (==6.3.2)
Project-URL: Repository, https://github.com/AAtley/triplify_csv
